solvecube/Cubie.py
solvecube/CubieCube.py
solvecube/Enums.py
solvecube/Face.py
solvecube/FaceCube.py
solvecube/Move.py
solvecube/NaiveCube.py
solvecube/Printer.py
solvecube/__init__.py
solvecube/utils.py
solvecube/CoordCube/__init__.py
solvecube/Solver/__init__.py
solvecube/Solver/Beginner/SecondLayerSolver.py
solvecube/Solver/Beginner/WhiteCrossSolver.py
solvecube/Solver/Beginner/WhiteFaceSolver.py
solvecube/Solver/Beginner/YellowCrossSolver.py
solvecube/Solver/Beginner/YellowFaceSolver.py
solvecube/Solver/Beginner/__init__.py
solvecube/Solver/CFOP/F2LSolver.py
solvecube/Solver/CFOP/OLLSolver.py
solvecube/Solver/CFOP/PLLSolver.py
solvecube/Solver/CFOP/__init__.py
solvecube/Solver/Kociemba/Search.py
solvecube/Solver/Kociemba/__init__.py
solvecube-0.0.4.dist-info/LICENSE
solvecube-0.0.4.dist-info/METADATA
solvecube-0.0.4.dist-info/WHEEL
solvecube-0.0.4.dist-info/entry_points.txt
solvecube-0.0.4.dist-info/top_level.txt
solvecube-0.0.4.dist-info/RECORD
