Metadata-Version: 2.1
Name: solvecube
Version: 0.0.4
Summary: Rubik solver algorithms
Home-page: UNKNOWN
Author: Abir Abedin Khan
Author-email: abirabedinkhan@yahoo.com
License: UNKNOWN
Platform: UNKNOWN
Classifier: Development Status :: 3 - Alpha
Classifier: License :: OSI Approved :: MIT License
Classifier: Programming Language :: Python :: 2.7
Classifier: Programming Language :: Python :: 3.3
Classifier: Programming Language :: Python :: 3.4
Classifier: Programming Language :: Python :: 3.5
Classifier: Programming Language :: Python :: 3.6
Requires-Dist: future (==0.16.0)
